tests/__init__.py
tests/test_whatsappchattodf.py
whatsappchattodf/__init__.py
whatsappchattodf/whatsappchattodf.py
whatsappchattodf-0.1.2.dist-info/LICENSE
whatsappchattodf-0.1.2.dist-info/METADATA
whatsappchattodf-0.1.2.dist-info/WHEEL
whatsappchattodf-0.1.2.dist-info/entry_points.txt
whatsappchattodf-0.1.2.dist-info/top_level.txt
whatsappchattodf-0.1.2.dist-info/RECORD
