Metadata-Version: 2.1
Name: whatsappchattodf
Version: 0.1.2
Summary: Convert WhatsApp chat logs (.txt) to a pandas DataFrame.
Home-page: https://github.com/kartheekpnsn/whatsappchattodf
Author: Kartheek Palepu
Author-email: kartheekpnsn@gmail.com
Classifier: Programming Language :: Python :: 3
Classifier: License :: OSI Approved :: MIT License
Classifier: Operating System :: OS Independent
Requires-Python: >=3.6
License-File: LICENSE
Requires-Dist: pandas >=1.0.0
